tox/__init__.py
tox/__main__.py
tox/provision.py
tox/py.typed
tox/pytest.py
tox/report.py
tox/run.py
tox/tox.schema.json
tox/version.py
tox/config/__init__.py
tox/config/main.py
tox/config/of_type.py
tox/config/set_env.py
tox/config/sets.py
tox/config/types.py
tox/config/cli/__init__.py
tox/config/cli/env_var.py
tox/config/cli/ini.py
tox/config/cli/parse.py
tox/config/cli/parser.py
tox/config/loader/__init__.py
tox/config/loader/api.py
tox/config/loader/convert.py
tox/config/loader/memory.py
tox/config/loader/replacer.py
tox/config/loader/section.py
tox/config/loader/str_convert.py
tox/config/loader/stringify.py
tox/config/loader/ini/__init__.py
tox/config/loader/ini/factor.py
tox/config/loader/ini/replace.py
tox/config/loader/toml/__init__.py
tox/config/loader/toml/_api.py
tox/config/loader/toml/_replace.py
tox/config/loader/toml/_validate.py
tox/config/source/__init__.py
tox/config/source/api.py
tox/config/source/discover.py
tox/config/source/ini.py
tox/config/source/ini_section.py
tox/config/source/legacy_toml.py
tox/config/source/setup_cfg.py
tox/config/source/toml_pyproject.py
tox/config/source/toml_tox.py
tox/config/source/tox_ini.py
tox/execute/__init__.py
tox/execute/api.py
tox/execute/pep517_backend.py
tox/execute/request.py
tox/execute/stream.py
tox/execute/util.py
tox/execute/local_sub_process/__init__.py
tox/execute/local_sub_process/read_via_thread.py
tox/execute/local_sub_process/read_via_thread_unix.py
tox/execute/local_sub_process/read_via_thread_windows.py
tox/journal/__init__.py
tox/journal/env.py
tox/journal/main.py
tox/plugin/__init__.py
tox/plugin/inline.py
tox/plugin/manager.py
tox/plugin/spec.py
tox/session/__init__.py
tox/session/env_select.py
tox/session/state.py
tox/session/cmd/__init__.py
tox/session/cmd/depends.py
tox/session/cmd/devenv.py
tox/session/cmd/exec_.py
tox/session/cmd/legacy.py
tox/session/cmd/list_env.py
tox/session/cmd/quickstart.py
tox/session/cmd/schema.py
tox/session/cmd/show_config.py
tox/session/cmd/version_flag.py
tox-4.34.0.dist-info/METADATA
tox-4.34.0.dist-info/WHEEL
tox-4.34.0.dist-info/entry_points.txt
tox-4.34.0.dist-info/licenses/LICENSE
tox-4.34.0.dist-info/RECORD
