Metadata-Version: 2.4
Name: tox
Version: 4.34.0
Summary: tox is a generic virtualenv management and test command line tool
Project-URL: Documentation, https://tox.wiki
Project-URL: Homepage, http://tox.readthedocs.org
Project-URL: Release Notes, https://tox.wiki/en/latest/changelog.html
Project-URL: Source, https://github.com/tox-dev/tox
Project-URL: Tracker, https://github.com/tox-dev/tox/issues
Author-email: Bernát Gábor <gaborjbernat@gmail.com>
Maintainer-email: Anthony Sottile <asottile@umich.edu>, Bernát Gábor <gaborjbernat@gmail.com>, Jürgen Gmach <juergen.gmach@googlemail.com>, Oliver Bestwalter <oliver@bestwalter.de>
License-Expression: MIT
License-File: LICENSE
Keywords: environments,isolated,testing,virtual
Classifier: Development Status :: 5 - Production/Stable
Classifier: Framework :: tox
Classifier: Intended Audience :: Developers
Classifier: License :: OSI Approved :: MIT License
Classifier: Operating System :: MacOS :: MacOS X
Classifier: Operating System :: Microsoft :: Windows
Classifier: Operating System :: POSIX
Classifier: Programming Language :: Python :: 3 :: Only
Classifier: Programming Language :: Python :: 3.10
Classifier: Programming Language :: Python :: 3.11
Classifier: Programming Language :: Python :: 3.12
Classifier: Programming Language :: Python :: 3.13
Classifier: Programming Language :: Python :: 3.14
Classifier: Topic :: Software Development :: Libraries
Classifier: Topic :: Software Development :: Testing
Classifier: Topic :: Utilities
Requires-Python: >=3.10
Requires-Dist: cachetools>=6.2.4
Requires-Dist: chardet>=5.2
Requires-Dist: colorama>=0.4.6
Requires-Dist: filelock>=3.20.2
Requires-Dist: packaging>=25
Requires-Dist: platformdirs>=4.5.1
Requires-Dist: pluggy>=1.6
Requires-Dist: pyproject-api>=1.10
Requires-Dist: tomli>=2.3; python_version < '3.11'
Requires-Dist: typing-extensions>=4.15; python_version < '3.11'
Requires-Dist: virtualenv>=20.35.4
